ffpyplayer/writer.pyx
ffpyplayer/pic.pxd
ffpyplayer/threading.pyx
ffpyplayer/tools.pyx
ffpyplayer/pic.cpython-313-darwin.so
ffpyplayer/writer.cpython-313-darwin.so
ffpyplayer/__init__.py
ffpyplayer/tools.cpython-313-darwin.so
ffpyplayer/threading.pxd
ffpyplayer/threading.cpython-313-darwin.so
ffpyplayer/pic.pyx
ffpyplayer/writer.pxd
ffpyplayer/clib/misc.h
ffpyplayer/clib/misc.c
ffpyplayer/tests/test_play.py
ffpyplayer/tests/__init__.py
ffpyplayer/tests/common.py
ffpyplayer/tests/test_write.py
ffpyplayer/tests/test_pic.py
ffpyplayer/includes/sdl.pxi
ffpyplayer/includes/inline_funcs.pxi
ffpyplayer/includes/ffconfig.h
ffpyplayer/includes/ffconfig.pxi
ffpyplayer/includes/ffmpeg.pxi
ffpyplayer/includes/ff_consts.pxi
ffpyplayer/.dylibs/libavdevice.60.1.100.dylib
ffpyplayer/.dylibs/libvorbisenc.2.dylib
ffpyplayer/.dylibs/libtheoradec.2.dylib
ffpyplayer/.dylibs/libavcodec.60.3.100.dylib
ffpyplayer/.dylibs/libpostproc.57.1.100.dylib
ffpyplayer/.dylibs/libz.1.2.13.dylib
ffpyplayer/.dylibs/libx264.164.dylib
ffpyplayer/.dylibs/libswscale.7.1.100.dylib
ffpyplayer/.dylibs/libavfilter.9.3.100.dylib
ffpyplayer/.dylibs/libtheoraenc.2.dylib
ffpyplayer/.dylibs/libSDL2-2.0.0.dylib
ffpyplayer/.dylibs/libpng16.16.dylib
ffpyplayer/.dylibs/libavformat.60.3.100.dylib
ffpyplayer/.dylibs/libssl.3.dylib
ffpyplayer/.dylibs/libmp3lame.0.dylib
ffpyplayer/.dylibs/libfreetype.6.dylib
ffpyplayer/.dylibs/libcrypto.3.dylib
ffpyplayer/.dylibs/libharfbuzz.0.dylib
ffpyplayer/.dylibs/libfribidi.0.dylib
ffpyplayer/.dylibs/libass.9.dylib
ffpyplayer/.dylibs/libvorbis.0.dylib
ffpyplayer/.dylibs/libfdk-aac.2.0.2.dylib
ffpyplayer/.dylibs/libswresample.4.10.100.dylib
ffpyplayer/.dylibs/liblzma.5.dylib
ffpyplayer/.dylibs/libbrotlidec.1.0.9.dylib
ffpyplayer/.dylibs/libavutil.58.2.100.dylib
ffpyplayer/.dylibs/libbrotlicommon.1.0.9.dylib
ffpyplayer/.dylibs/libvpx.9.dylib
ffpyplayer/.dylibs/libogg.0.dylib
ffpyplayer/.dylibs/libopus.0.dylib
ffpyplayer-4.5.3.dist-info/RECORD
ffpyplayer-4.5.3.dist-info/WHEEL
ffpyplayer-4.5.3.dist-info/top_level.txt
ffpyplayer-4.5.3.dist-info/METADATA
ffpyplayer-4.5.3.dist-info/licenses/COPYING
